docoreai_autopatch.pth
Python313/Lib/site-packages/docoreai_autopatch.pth
api/__init__.py
api/main.py
docore_ai/__init__.py
docore_ai/auto_patch.py
docore_ai/cli.py
docore_ai/demo_failed_auto_patch.py
docore_ai/fusion_log_server.py
docore_ai/init_engine.py
docore_ai/model.py
docore_ai/patcher.py
docore_ai/proxy.py
docore_ai/pth_installer.py
docore_ai/test_server.py
docore_ai/prompt_updates/__init__.py
docore_ai/prompt_updates/check_prompt_update.py
docore_ai/prompt_updates/prompt_loader.py
docore_ai/telemetry/.docoreai_usage.json
docore_ai/telemetry/__init__.py
docore_ai/telemetry/config.py
docore_ai/telemetry/safe_sender.py
docore_ai/telemetry/safe_sender1.py
docore_ai/telemetry/telemetry_wp.py
docore_ai/telemetry/token_auth.py
docore_ai/telemetry/token_utils.py
docore_ai/telemetry/tracker.py
docore_ai/telemetry/usage_limits.py
docore_ai/utils/__init__.py
docore_ai/utils/csv_logger.py
docore_ai/utils/docoreai_log.csv
docore_ai/utils/helpers.py
docore_ai/utils/logger.py
docore_ai/utils/run_streamlit_with_shutdown.py
docore_ai/utils/show_app.py
docore_ai/utils/show_app1.py
docoreai-1.0.1.dist-info/licenses/LICENSE.md
docoreai-1.0.1.dist-info/METADATA
docoreai-1.0.1.dist-info/WHEEL
docoreai-1.0.1.dist-info/entry_points.txt
docoreai-1.0.1.dist-info/top_level.txt
docoreai-1.0.1.dist-info/RECORD
