Metadata-Version: 2.4
Name: docoreai
Version: 1.0.1
Summary: DoCoreAI is an AI prompt optimization tool for developers and teams to reduce LLM cost, improve output, and analyze GPT prompt efficiency—no fine-tuning needed.
Home-page: https://docoreai.com
Author: Saji John Miranda
Author-email: info@docoreai.com
License: CC BY-NC-ND 4.0
Project-URL: Homepage, https://docoreai.com
Project-URL: Documentation, https://docoreai.com/docs/
Project-URL: Source Code, https://github.com/SajiJohnMiranda/DoCoreAI
Project-URL: Blog Post, https://mobilights.medium.com/intelligent-prompt-optimization-bac89b64fa84
Project-URL: Funding, https://docoreai.com/pricing/
Project-URL: Support, https://docoreai.com/contact-us
Keywords: openai,groq,prompt optimization,llm cost reduction,ai development,prompt tuning,gpt efficiency,docoreai
Classifier: Development Status :: 4 - Beta
Classifier: Programming Language :: Python :: 3
Classifier: Operating System :: OS Independent
Classifier: License :: Other/Proprietary License
Classifier: Intended Audience :: Developers
Classifier: Topic :: Software Development :: Libraries :: Python Modules
Classifier: Topic :: Scientific/Engineering :: Artificial Intelligence
Requires-Python: >=3.7
License-File: LICENSE.md
Requires-Dist: uvicorn
Requires-Dist: pydantic
Requires-Dist: fastapi
Requires-Dist: python-dotenv
Requires-Dist: openai
Requires-Dist: groq
Requires-Dist: requests
Requires-Dist: tiktoken
Requires-Dist: typer
Requires-Dist: rich
Requires-Dist: click
Requires-Dist: setuptools>=40.0.0
Requires-Dist: psutil>=5.9.0
Requires-Dist: importlib-metadata; python_version < "3.8"
Requires-Dist: packaging>=20.0
Requires-Dist: streamlit
Requires-Dist: pandas
Requires-Dist: streamlit-aggrid
Dynamic: author
Dynamic: author-email
Dynamic: classifier
Dynamic: description
Dynamic: description-content-type
Dynamic: home-page
Dynamic: keywords
Dynamic: license
Dynamic: license-file
Dynamic: project-url
Dynamic: requires-dist
Dynamic: requires-python
Dynamic: summary
